mxmul_pkg/__init__.py
mxmul_pkg/tommy_time.py
tommy_time0424-0.1.0.dist-info/LICENSE
tommy_time0424-0.1.0.dist-info/METADATA
tommy_time0424-0.1.0.dist-info/WHEEL
tommy_time0424-0.1.0.dist-info/top_level.txt
tommy_time0424-0.1.0.dist-info/RECORD
